{
  "illicit_l8hl88kzru": [
    "Directly identified as an illicit wallet"
  ],
  "exchange_xmxb9yo18p": [
    "High fan-out behavior (many outgoing transactions)",
    "High fan-in behavior (many incoming transactions)",
    "Highly central wallet in the transaction network",
    "High heuristic risk score based on rule-based behavioral analysis"
  ],
  "w_rtj5pht0hl": [
    "Wallet shows no significant behavioral or structural risk indicators."
  ],
  "exchange_smado8e7fl": [
    "High fan-out behavior (many outgoing transactions)",
    "High fan-in behavior (many incoming transactions)",
    "Highly central wallet in the transaction network",
    "High heuristic risk score based on rule-based behavioral analysis"
  ],
  "exchange_ajssuuqo1v": [
    "High fan-out behavior (many outgoing transactions)",
    "High fan-in behavior (many incoming transactions)",
    "Highly central wallet in the transaction network",
    "High heuristic risk score based on rule-based behavioral analysis"
  ],
  "w_ywd14ve92m": [
    "Wallet shows no significant behavioral or structural risk indicators."
  ],
  "w_q46nouhfj7": [
    "Wallet shows moderate activity with some risk indicators, but no strong illicit signals."
  ],
  "w_pki7p5tb94": [
    "Wallet exhibits elevated risk indicators but does not strongly resemble known illicit structures."
  ],
  "mixer_spengwyx9t": [
    "High fan-out behavior (many outgoing transactions)",
    "High fan-in behavior (many incoming transactions)",
    "High heuristic risk score based on rule-based behavioral analysis"
  ],
  "illicit_dw2zcfzw0l": [
    "Directly identified as an illicit wallet",
    "High fan-out behavior (many outgoing transactions)"
  ],
  "w_rht7zewviy": [
    "Wallet shows moderate activity with some risk indicators, but no strong illicit signals."
  ],
  "w_6hid25owf7": [
    "Wallet shows no significant behavioral or structural risk indicators."
  ],
  "exchange_qhrrpzlk3e": [
    "High fan-out behavior (many outgoing transactions)",
    "High fan-in behavior (many incoming transactions)",
    "Highly central wallet in the transaction network",
    "High heuristic risk score based on rule-based behavioral analysis"
  ],
  "w_zpeal2w37d": [
    "Wallet shows no significant behavioral or structural risk indicators."
  ],
  "w_jeget1ghr0": [
    "Wallet shows no significant behavioral or structural risk indicators."
  ],
  "w_6t4ufel624": [
    "Wallet shows no significant behavioral or structural risk indicators."
  ],
  "illicit_prcjiwvhdk": [
    "Directly identified as an illicit wallet",
    "High fan-out behavior (many outgoing transactions)"
  ],
  "illicit_wixz2c9ros": [
    "Directly identified as an illicit wallet"
  ],
  "w_x4w6xlpu0d": [
    "Wallet shows no significant behavioral or structural risk indicators."
  ],
  "mixer_3zkwdeekgy": [
    "High fan-out behavior (many outgoing transactions)",
    "High fan-in behavior (many incoming transactions)",
    "High heuristic risk score based on rule-based behavioral analysis"
  ],
  "w_lz049enulq": [
    "Wallet shows no significant behavioral or structural risk indicators."
  ],
  "exchange_4xyf9igfu8": [
    "High fan-in behavior (many incoming transactions)"
  ],
  "w_zlma5uofwb": [
    "Wallet shows no significant behavioral or structural risk indicators."
  ],
  "w_uhxid4n1u3": [
    "Wallet shows no significant behavioral or structural risk indicators."
  ],
  "mixer_j5sxvwvm4w": [
    "High fan-out behavior (many outgoing transactions)",
    "High fan-in behavior (many incoming transactions)",
    "High heuristic risk score based on rule-based behavioral analysis"
  ],
  "w_uk9e1v2isq": [
    "Wallet shows no significant behavioral or structural risk indicators."
  ],
  "illicit_in3oeuvtyt": [
    "Directly identified as an illicit wallet"
  ],
  "w_xxva2ieuc1": [
    "Wallet shows no significant behavioral or structural risk indicators."
  ],
  "w_yz7srcbplj": [
    "Wallet shows no significant behavioral or structural risk indicators."
  ],
  "w_hzlm72jeyn": [
    "Wallet shows no significant behavioral or structural risk indicators."
  ],
  "w_0y9dom5igq": [
    "Wallet shows no significant behavioral or structural risk indicators."
  ],
  "w_twdl9zs13c": [
    "Wallet shows no significant behavioral or structural risk indicators."
  ],
  "w_tz0yncxll4": [
    "Wallet shows moderate activity with some risk indicators, but no strong illicit signals."
  ],
  "w_tqvdz4x1zh": [
    "Wallet shows moderate activity with some risk indicators, but no strong illicit signals."
  ],
  "w_y8fv2bc2nn": [
    "Wallet shows no significant behavioral or structural risk indicators."
  ],
  "w_v5g10ur5l8": [
    "Wallet shows no significant behavioral or structural risk indicators."
  ],
  "w_odro8bnp84": [
    "Wallet shows no significant behavioral or structural risk indicators."
  ],
  "w_hsahxthv3a": [
    "Wallet shows no significant behavioral or structural risk indicators."
  ],
  "w_uww5wfcpkj": [
    "Wallet shows no significant behavioral or structural risk indicators."
  ],
  "illicit_dalmjegqto": [
    "Directly identified as an illicit wallet",
    "High fan-out behavior (many outgoing transactions)"
  ],
  "w_vslwf90km3": [
    "Wallet shows no significant behavioral or structural risk indicators."
  ],
  "w_jidknwi5fl": [
    "Wallet shows moderate activity with some risk indicators, but no strong illicit signals."
  ],
  "w_9xqym52xg8": [
    "Wallet shows no significant behavioral or structural risk indicators."
  ],
  "w_5935a0l725": [
    "Wallet shows no significant behavioral or structural risk indicators."
  ],
  "w_fwyjxrpj1e": [
    "Wallet shows no significant behavioral or structural risk indicators."
  ],
  "w_0s0r2sds8b": [
    "Wallet shows no significant behavioral or structural risk indicators."
  ],
  "w_ckjlteiyzc": [
    "Wallet shows no significant behavioral or structural risk indicators."
  ],
  "w_r6k2vmwwyz": [
    "Wallet shows no significant behavioral or structural risk indicators."
  ],
  "mixer_zh13cd5glq": [
    "High fan-out behavior (many outgoing transactions)",
    "High fan-in behavior (many incoming transactions)",
    "High heuristic risk score based on rule-based behavioral analysis"
  ],
  "w_30t9nt3w5u": [
    "Wallet shows no significant behavioral or structural risk indicators."
  ],
  "w_r97y2lofn1": [
    "Wallet shows no significant behavioral or structural risk indicators."
  ],
  "w_kbp2qd6vas": [
    "Wallet shows no significant behavioral or structural risk indicators."
  ],
  "w_3nx39rbsv5": [
    "Wallet shows no significant behavioral or structural risk indicators."
  ],
  "w_o75rh8lx6d": [
    "Wallet shows no significant behavioral or structural risk indicators."
  ],
  "w_csk30lvylk": [
    "Wallet shows no significant behavioral or structural risk indicators."
  ],
  "w_zbikcidkwn": [
    "Wallet shows no significant behavioral or structural risk indicators."
  ],
  "w_zklookep7y": [
    "Wallet shows no significant behavioral or structural risk indicators."
  ],
  "w_pnsm43d8w3": [
    "Wallet shows no significant behavioral or structural risk indicators."
  ],
  "w_3qsqcq30o3": [
    "Wallet shows no significant behavioral or structural risk indicators."
  ],
  "w_sqt26q3xlr": [
    "Wallet shows no significant behavioral or structural risk indicators."
  ],
  "w_rxdouadvwk": [
    "Wallet shows no significant behavioral or structural risk indicators."
  ],
  "illicit_8lw2lm349e": [
    "Directly identified as an illicit wallet"
  ],
  "w_25sq8croyr": [
    "Wallet shows no significant behavioral or structural risk indicators."
  ],
  "w_5bcw790pdw": [
    "Wallet shows no significant behavioral or structural risk indicators."
  ],
  "w_18k0axycel": [
    "Wallet shows no significant behavioral or structural risk indicators."
  ],
  "w_3j2d54i3qk": [
    "Wallet shows no significant behavioral or structural risk indicators."
  ],
  "w_upfln4rxyj": [
    "Wallet exhibits elevated risk indicators but does not strongly resemble known illicit structures."
  ],
  "w_ef0votqtxh": [
    "Wallet shows no significant behavioral or structural risk indicators."
  ],
  "w_5jsg65kxvf": [
    "Wallet shows no significant behavioral or structural risk indicators."
  ],
  "w_cfi4o6l1f9": [
    "Wallet shows no significant behavioral or structural risk indicators."
  ],
  "illicit_amdvlnknd6": [
    "Directly identified as an illicit wallet",
    "High fan-out behavior (many outgoing transactions)"
  ],
  "w_k6re4q6qdy": [
    "Wallet shows no significant behavioral or structural risk indicators."
  ],
  "w_psfnkomv2x": [
    "Wallet shows no significant behavioral or structural risk indicators."
  ],
  "w_8ut0cvs4f8": [
    "Wallet shows no significant behavioral or structural risk indicators."
  ],
  "w_ylurtp0lzj": [
    "Wallet shows no significant behavioral or structural risk indicators."
  ],
  "w_45bm1enf31": [
    "Wallet shows no significant behavioral or structural risk indicators."
  ],
  "w_64jwtektsg": [
    "Wallet shows no significant behavioral or structural risk indicators."
  ],
  "w_dtbh55rbc7": [
    "Wallet shows no significant behavioral or structural risk indicators."
  ],
  "w_9t7e8g8jdp": [
    "Wallet shows no significant behavioral or structural risk indicators."
  ],
  "w_lxslg6mm1z": [
    "Wallet shows no significant behavioral or structural risk indicators."
  ],
  "w_2sehe2atn2": [
    "Wallet shows no significant behavioral or structural risk indicators."
  ],
  "w_38xrg2gzr7": [
    "Wallet shows no significant behavioral or structural risk indicators."
  ],
  "w_qacj4t0sek": [
    "Wallet shows moderate activity with some risk indicators, but no strong illicit signals."
  ],
  "w_txcb48y1o4": [
    "Wallet shows no significant behavioral or structural risk indicators."
  ],
  "w_tzk3ny9v20": [
    "Wallet shows no significant behavioral or structural risk indicators."
  ],
  "w_m25len606n": [
    "Wallet shows no significant behavioral or structural risk indicators."
  ],
  "w_dzr1yxr2dh": [
    "Wallet exhibits elevated risk indicators but does not strongly resemble known illicit structures."
  ],
  "w_z4z7whwkmy": [
    "Wallet shows no significant behavioral or structural risk indicators."
  ],
  "w_60rjiw1swj": [
    "Wallet shows no significant behavioral or structural risk indicators."
  ],
  "w_es6m033ifh": [
    "Wallet shows no significant behavioral or structural risk indicators."
  ],
  "w_objlzy1uu9": [
    "Wallet shows no significant behavioral or structural risk indicators."
  ],
  "w_qimqodpxnf": [
    "Wallet shows no significant behavioral or structural risk indicators."
  ],
  "w_pkyrybovak": [
    "Wallet shows no significant behavioral or structural risk indicators."
  ],
  "w_hqmabsi9nb": [
    "Wallet shows no significant behavioral or structural risk indicators."
  ],
  "w_lemx15z8vm": [
    "Wallet shows no significant behavioral or structural risk indicators."
  ],
  "w_jgxaa2ilgb": [
    "Wallet shows moderate activity with some risk indicators, but no strong illicit signals."
  ],
  "w_ihx74d0gjy": [
    "Wallet shows no significant behavioral or structural risk indicators."
  ],
  "w_9mx2x18haf": [
    "Wallet shows no significant behavioral or structural risk indicators."
  ],
  "w_6ub7l8v1zo": [
    "Wallet shows no significant behavioral or structural risk indicators."
  ],
  "w_s1k9ye9o2m": [
    "Wallet shows no significant behavioral or structural risk indicators."
  ],
  "w_0hpmnz1udb": [
    "Wallet shows moderate activity with some risk indicators, but no strong illicit signals."
  ],
  "w_xux1oxrwk8": [
    "Wallet shows no significant behavioral or structural risk indicators."
  ],
  "w_atatj9a3y3": [
    "Wallet shows no significant behavioral or structural risk indicators."
  ],
  "w_rcnbh6nqqb": [
    "Wallet shows no significant behavioral or structural risk indicators."
  ],
  "w_0lvsnujza7": [
    "Wallet shows moderate activity with some risk indicators, but no strong illicit signals."
  ],
  "w_qx6gvwrdml": [
    "Wallet shows no significant behavioral or structural risk indicators."
  ],
  "w_azytjxepq8": [
    "Wallet shows no significant behavioral or structural risk indicators."
  ],
  "illicit_1bj9rm7pyx": [
    "Directly identified as an illicit wallet"
  ],
  "illicit_8qzpky32or": [
    "Directly identified as an illicit wallet"
  ],
  "w_xpj4hnriuu": [
    "Wallet shows no significant behavioral or structural risk indicators."
  ],
  "w_7fxzv4u3bb": [
    "Wallet shows moderate activity with some risk indicators, but no strong illicit signals."
  ],
  "w_waouaxeqbn": [
    "Wallet shows no significant behavioral or structural risk indicators."
  ],
  "w_qlgzui1b0z": [
    "Wallet shows no significant behavioral or structural risk indicators."
  ],
  "w_vifttd96qe": [
    "Wallet shows no significant behavioral or structural risk indicators."
  ],
  "w_43c5ba75uu": [
    "Wallet shows no significant behavioral or structural risk indicators."
  ],
  "w_x63cfl0uke": [
    "Wallet shows no significant behavioral or structural risk indicators."
  ],
  "w_yrvxoieves": [
    "Wallet shows no significant behavioral or structural risk indicators."
  ],
  "w_bhb7s9tj1g": [
    "Wallet shows moderate activity with some risk indicators, but no strong illicit signals."
  ],
  "w_8hmbr5xqt4": [
    "Wallet shows moderate activity with some risk indicators, but no strong illicit signals."
  ],
  "illicit_69ugnekrcp": [
    "Directly identified as an illicit wallet",
    "High fan-out behavior (many outgoing transactions)"
  ],
  "w_2iagl58kxo": [
    "Wallet shows no significant behavioral or structural risk indicators."
  ],
  "w_j2qp89uzfk": [
    "Wallet shows no significant behavioral or structural risk indicators."
  ],
  "w_0s9bp4m18o": [
    "Wallet shows no significant behavioral or structural risk indicators."
  ],
  "w_owgzrixa11": [
    "Wallet shows moderate activity with some risk indicators, but no strong illicit signals."
  ],
  "w_yar821uzvg": [
    "Wallet shows no significant behavioral or structural risk indicators."
  ],
  "w_dyt9moge4q": [
    "Wallet shows no significant behavioral or structural risk indicators."
  ],
  "w_3r30me8f84": [
    "Wallet shows no significant behavioral or structural risk indicators."
  ],
  "w_6ccvcjwtl9": [
    "Wallet shows no significant behavioral or structural risk indicators."
  ],
  "w_zhwjr64dpj": [
    "Wallet shows no significant behavioral or structural risk indicators."
  ],
  "w_fm8zov7ln2": [
    "Wallet shows no significant behavioral or structural risk indicators."
  ],
  "w_or7875aud9": [
    "Wallet shows no significant behavioral or structural risk indicators."
  ],
  "w_fxhkc856wp": [
    "Wallet shows no significant behavioral or structural risk indicators."
  ],
  "w_4lmct64z7w": [
    "Wallet shows no significant behavioral or structural risk indicators."
  ],
  "w_j43d5iqvnb": [
    "Wallet shows no significant behavioral or structural risk indicators."
  ],
  "w_hl1n13jcat": [
    "Wallet shows no significant behavioral or structural risk indicators."
  ],
  "exchange_iogxpbwhvn": [
    "Wallet shows moderate activity with some risk indicators, but no strong illicit signals."
  ],
  "w_9xuy41iblj": [
    "Wallet shows no significant behavioral or structural risk indicators."
  ],
  "w_myx444nlz1": [
    "Wallet shows no significant behavioral or structural risk indicators."
  ],
  "w_3rzsj49itn": [
    "Wallet shows no significant behavioral or structural risk indicators."
  ],
  "w_xfgcaqvkiz": [
    "Wallet shows no significant behavioral or structural risk indicators."
  ],
  "w_2m0w10lbt3": [
    "Wallet shows no significant behavioral or structural risk indicators."
  ],
  "w_ww4fyb8dal": [
    "Wallet shows no significant behavioral or structural risk indicators."
  ],
  "w_5psq0oxfq8": [
    "Wallet shows moderate activity with some risk indicators, but no strong illicit signals."
  ],
  "w_fcd6mzsgip": [
    "Wallet exhibits elevated risk indicators but does not strongly resemble known illicit structures."
  ],
  "w_wd7oi0pesg": [
    "Wallet shows no significant behavioral or structural risk indicators."
  ],
  "w_9382kkzmpj": [
    "Wallet shows no significant behavioral or structural risk indicators."
  ],
  "w_cslqc3c54w": [
    "Wallet shows no significant behavioral or structural risk indicators."
  ],
  "w_hejla0gnzs": [
    "Wallet shows no significant behavioral or structural risk indicators."
  ],
  "w_3sdygfliji": [
    "Wallet shows moderate activity with some risk indicators, but no strong illicit signals."
  ],
  "w_kkv9rftmtt": [
    "Wallet shows no significant behavioral or structural risk indicators."
  ],
  "w_6ddfgs3jon": [
    "Wallet shows no significant behavioral or structural risk indicators."
  ],
  "w_hc36kof8kr": [
    "Wallet shows no significant behavioral or structural risk indicators."
  ],
  "w_k0get8t63j": [
    "Wallet shows no significant behavioral or structural risk indicators."
  ],
  "w_uxg2myr06n": [
    "Wallet shows no significant behavioral or structural risk indicators."
  ],
  "w_5py6b2knft": [
    "Wallet shows no significant behavioral or structural risk indicators."
  ],
  "w_eyuhz1gv0e": [
    "Wallet shows no significant behavioral or structural risk indicators."
  ],
  "w_j70e3p15ah": [
    "Wallet shows moderate activity with some risk indicators, but no strong illicit signals."
  ],
  "w_493wxa73jg": [
    "Wallet shows no significant behavioral or structural risk indicators."
  ],
  "w_xyvgiui9kk": [
    "Wallet shows no significant behavioral or structural risk indicators."
  ],
  "w_7oq2zdo74v": [
    "Wallet shows no significant behavioral or structural risk indicators."
  ],
  "w_a78e9rivh6": [
    "Wallet shows no significant behavioral or structural risk indicators."
  ],
  "w_6wktakpuxq": [
    "Wallet shows no significant behavioral or structural risk indicators."
  ],
  "w_gyggsnpuev": [
    "Wallet shows no significant behavioral or structural risk indicators."
  ],
  "w_ns832ejx5t": [
    "Wallet shows no significant behavioral or structural risk indicators."
  ],
  "w_l1cq99chj7": [
    "Wallet shows moderate activity with some risk indicators, but no strong illicit signals."
  ],
  "w_iaakytt3im": [
    "Wallet shows no significant behavioral or structural risk indicators."
  ],
  "w_d44k1j6fp8": [
    "Wallet shows no significant behavioral or structural risk indicators."
  ],
  "w_h024kwk585": [
    "Wallet shows no significant behavioral or structural risk indicators."
  ],
  "w_t1ntmjsrd9": [
    "Wallet shows no significant behavioral or structural risk indicators."
  ],
  "w_3fpoyipk0q": [
    "Wallet shows no significant behavioral or structural risk indicators."
  ],
  "w_dw2pcn9t84": [
    "Wallet shows no significant behavioral or structural risk indicators."
  ],
  "w_3kx7eedtjv": [
    "Wallet shows no significant behavioral or structural risk indicators."
  ],
  "w_u2gc5wi6fq": [
    "Wallet shows no significant behavioral or structural risk indicators."
  ],
  "w_hh5lf6a4fe": [
    "Wallet shows no significant behavioral or structural risk indicators."
  ],
  "w_874frhocn9": [
    "Wallet shows no significant behavioral or structural risk indicators."
  ],
  "w_r2ykccprhv": [
    "Wallet shows moderate activity with some risk indicators, but no strong illicit signals."
  ],
  "w_9tze5r5uqp": [
    "Wallet shows no significant behavioral or structural risk indicators."
  ],
  "w_y4lyk83tql": [
    "Wallet shows no significant behavioral or structural risk indicators."
  ],
  "illicit_7yt2m6twd1": [
    "Directly identified as an illicit wallet"
  ],
  "w_izasnwywrr": [
    "Wallet shows no significant behavioral or structural risk indicators."
  ],
  "w_cgvyie6ivw": [
    "Wallet shows moderate activity with some risk indicators, but no strong illicit signals."
  ],
  "w_7c3dd03uvu": [
    "Wallet shows no significant behavioral or structural risk indicators."
  ],
  "w_5050ui22kx": [
    "Wallet shows no significant behavioral or structural risk indicators."
  ],
  "w_tl3q4n89qk": [
    "Wallet shows no significant behavioral or structural risk indicators."
  ],
  "w_ianouof0on": [
    "Wallet shows no significant behavioral or structural risk indicators."
  ],
  "w_hhpbmyofqe": [
    "Wallet shows no significant behavioral or structural risk indicators."
  ],
  "w_0982n2atqy": [
    "Wallet shows moderate activity with some risk indicators, but no strong illicit signals."
  ],
  "w_0ubmc97c7b": [
    "Wallet shows no significant behavioral or structural risk indicators."
  ],
  "w_fyo1750ceh": [
    "Wallet exhibits elevated risk indicators but does not strongly resemble known illicit structures."
  ],
  "w_lc58drc11e": [
    "Wallet shows no significant behavioral or structural risk indicators."
  ],
  "w_2voi8uyyf1": [
    "Wallet shows no significant behavioral or structural risk indicators."
  ],
  "w_c8ra484nl6": [
    "Wallet shows no significant behavioral or structural risk indicators."
  ],
  "w_qjg02u1g46": [
    "Wallet shows no significant behavioral or structural risk indicators."
  ],
  "w_3y30ysxpnn": [
    "Wallet shows no significant behavioral or structural risk indicators."
  ],
  "w_7s55j2o7s3": [
    "Wallet shows moderate activity with some risk indicators, but no strong illicit signals."
  ],
  "w_ifpwioxd9c": [
    "Wallet shows no significant behavioral or structural risk indicators."
  ],
  "w_31yihair4c": [
    "Wallet shows no significant behavioral or structural risk indicators."
  ],
  "w_uvy8n1utox": [
    "Wallet shows no significant behavioral or structural risk indicators."
  ],
  "w_i15cqzcuct": [
    "Wallet shows no significant behavioral or structural risk indicators."
  ],
  "w_pvs7hzioyk": [
    "Wallet shows no significant behavioral or structural risk indicators."
  ],
  "w_7ur23gdppq": [
    "Wallet shows no significant behavioral or structural risk indicators."
  ],
  "w_cwi64ciyhe": [
    "Wallet shows no significant behavioral or structural risk indicators."
  ],
  "w_k9tr74qgef": [
    "Wallet shows moderate activity with some risk indicators, but no strong illicit signals."
  ],
  "w_74x2ek3zez": [
    "Wallet shows no significant behavioral or structural risk indicators."
  ],
  "w_xaji0y6dpb": [
    "Wallet shows no significant behavioral or structural risk indicators."
  ],
  "w_l8os9xtogn": [
    "Wallet shows no significant behavioral or structural risk indicators."
  ],
  "w_g2qzw3c1qk": [
    "Wallet shows no significant behavioral or structural risk indicators."
  ],
  "w_twbozd1at7": [
    "Wallet shows no significant behavioral or structural risk indicators."
  ],
  "w_4gh2m5zja8": [
    "Wallet shows no significant behavioral or structural risk indicators."
  ],
  "w_zp08j3trp0": [
    "Wallet shows no significant behavioral or structural risk indicators."
  ],
  "w_yv37dia5u6": [
    "Wallet shows no significant behavioral or structural risk indicators."
  ],
  "w_nam148p0tv": [
    "Wallet shows no significant behavioral or structural risk indicators."
  ],
  "w_nhj7xvg0fn": [
    "Wallet shows moderate activity with some risk indicators, but no strong illicit signals."
  ],
  "w_hcbn9wszv8": [
    "Wallet shows no significant behavioral or structural risk indicators."
  ],
  "w_o119xp9n56": [
    "Wallet shows no significant behavioral or structural risk indicators."
  ],
  "w_zqy72wx7pt": [
    "Wallet shows no significant behavioral or structural risk indicators."
  ],
  "w_ss9toqw9ja": [
    "Wallet shows no significant behavioral or structural risk indicators."
  ],
  "w_dpg8sbi4q2": [
    "Wallet shows no significant behavioral or structural risk indicators."
  ],
  "w_9xpseimvih": [
    "Wallet shows no significant behavioral or structural risk indicators."
  ],
  "w_qg433e1i1p": [
    "Wallet shows no significant behavioral or structural risk indicators."
  ],
  "w_h75lxo6qji": [
    "Wallet shows no significant behavioral or structural risk indicators."
  ],
  "w_ujv6oh9sdb": [
    "Wallet shows no significant behavioral or structural risk indicators."
  ],
  "w_omtzzf8adf": [
    "Wallet shows no significant behavioral or structural risk indicators."
  ],
  "w_71hssbelrq": [
    "Wallet shows no significant behavioral or structural risk indicators."
  ],
  "w_sc4e5hrdu4": [
    "Wallet shows no significant behavioral or structural risk indicators."
  ],
  "w_d84u89yjb1": [
    "Wallet shows no significant behavioral or structural risk indicators."
  ],
  "w_ul1rsrla8s": [
    "Wallet shows no significant behavioral or structural risk indicators."
  ],
  "w_p49kwv08hh": [
    "Wallet shows no significant behavioral or structural risk indicators."
  ],
  "w_tlcxlvpymb": [
    "Wallet shows no significant behavioral or structural risk indicators."
  ],
  "w_phr62gdswm": [
    "Wallet shows no significant behavioral or structural risk indicators."
  ],
  "w_ut076g5g79": [
    "Wallet shows no significant behavioral or structural risk indicators."
  ],
  "w_jj8mgpp1no": [
    "Wallet shows no significant behavioral or structural risk indicators."
  ],
  "w_v1xg1r11q7": [
    "Wallet shows no significant behavioral or structural risk indicators."
  ],
  "w_1w1ht7pze9": [
    "Wallet shows no significant behavioral or structural risk indicators."
  ],
  "w_otohp6vz41": [
    "Wallet shows moderate activity with some risk indicators, but no strong illicit signals."
  ],
  "w_jja26yfpmv": [
    "Wallet shows no significant behavioral or structural risk indicators."
  ],
  "w_55nf4zw9xa": [
    "Wallet shows no significant behavioral or structural risk indicators."
  ],
  "w_a1wj0tpac5": [
    "Wallet shows no significant behavioral or structural risk indicators."
  ],
  "w_os6zle6kwh": [
    "Wallet shows no significant behavioral or structural risk indicators."
  ],
  "w_p501nouhtc": [
    "Wallet shows moderate activity with some risk indicators, but no strong illicit signals."
  ],
  "w_y981udp2fm": [
    "Wallet shows no significant behavioral or structural risk indicators."
  ],
  "w_ou9iy4x41d": [
    "Wallet exhibits elevated risk indicators but does not strongly resemble known illicit structures."
  ],
  "w_gh8riec4d1": [
    "Wallet shows moderate activity with some risk indicators, but no strong illicit signals."
  ],
  "w_r4kz36u8ue": [
    "Wallet shows moderate activity with some risk indicators, but no strong illicit signals."
  ],
  "w_ntcagrp2u4": [
    "Wallet shows no significant behavioral or structural risk indicators."
  ],
  "w_dbvzb0oih5": [
    "Wallet shows moderate activity with some risk indicators, but no strong illicit signals."
  ],
  "w_9skdgigatj": [
    "Wallet shows no significant behavioral or structural risk indicators."
  ],
  "w_9rr7s20cv3": [
    "Wallet shows no significant behavioral or structural risk indicators."
  ],
  "w_nyxtxmgtt0": [
    "Wallet shows no significant behavioral or structural risk indicators."
  ],
  "w_p6befflzm7": [
    "Wallet shows no significant behavioral or structural risk indicators."
  ],
  "w_ie0rnujjq9": [
    "Wallet shows no significant behavioral or structural risk indicators."
  ],
  "w_1t2tala753": [
    "Wallet shows no significant behavioral or structural risk indicators."
  ],
  "w_5m9j98cwn2": [
    "Wallet shows moderate activity with some risk indicators, but no strong illicit signals."
  ],
  "w_38daly8ozc": [
    "Wallet shows no significant behavioral or structural risk indicators."
  ],
  "w_0tgsiwg0od": [
    "Wallet shows no significant behavioral or structural risk indicators."
  ],
  "w_4ivsolmlgs": [
    "Wallet shows no significant behavioral or structural risk indicators."
  ],
  "w_3zmf8mdd4v": [
    "Wallet shows moderate activity with some risk indicators, but no strong illicit signals."
  ],
  "w_7sqrf1llks": [
    "Wallet shows no significant behavioral or structural risk indicators."
  ],
  "w_susmesjt2j": [
    "Wallet shows no significant behavioral or structural risk indicators."
  ],
  "w_cdyk0x65mu": [
    "Wallet shows no significant behavioral or structural risk indicators."
  ],
  "w_y9v86wzs3t": [
    "Wallet shows no significant behavioral or structural risk indicators."
  ],
  "w_suflsehuds": [
    "Wallet shows no significant behavioral or structural risk indicators."
  ],
  "w_9k9xjuy0bv": [
    "Wallet shows no significant behavioral or structural risk indicators."
  ],
  "w_gb7r3ocwbf": [
    "Wallet shows no significant behavioral or structural risk indicators."
  ],
  "w_1l7dypmlva": [
    "Wallet shows no significant behavioral or structural risk indicators."
  ],
  "w_zggm0j36tc": [
    "Wallet shows no significant behavioral or structural risk indicators."
  ],
  "w_zc0b4mskyv": [
    "Wallet shows no significant behavioral or structural risk indicators."
  ],
  "w_s1ssrkxlcd": [
    "Wallet shows no significant behavioral or structural risk indicators."
  ]
}